Metadata-Version: 2.4
Name: sgr-deep-research
Version: 0.5.0
Summary: SGR Agent Core - Schema-Guided Reasoning for building agent
Author: virrius, VaKovaLskii, abdullin, Pavel Zloi, Shadekss, mixaill76
License: MIT
Project-URL: Homepage, https://github.com/vakovalskii/sgr-deep-research
Project-URL: Repository, https://github.com/vakovalskii/sgr-deep-research
Project-URL: Issues, https://github.com/vakovalskii/sgr-deep-research/issues
Keywords: ai,research,reasoning,schema-guided,openai
Classifier: Development Status :: 3 - Alpha
Classifier: Intended Audience :: Developers
Classifier: Intended Audience :: Science/Research
Classifier: License :: OSI Approved :: MIT License
Classifier: Programming Language :: Python :: 3
Classifier: Programming Language :: Python :: 3.11
Classifier: Programming Language :: Python :: 3.12
Classifier: Programming Language :: Python :: 3.13
Classifier: Topic :: Scientific/Engineering :: Artificial Intelligence
Classifier: Topic :: Software Development :: Libraries :: Python Modules
Requires-Python: >=3.11
License-File: LICENSE
Requires-Dist: openai>=1.0.0
Requires-Dist: pydantic>=2.0.0
Requires-Dist: rich>=13.0.0
Requires-Dist: httpx>=0.25.0
Requires-Dist: socksio>=1.0.0
Requires-Dist: tavily-python>=0.3.0
Requires-Dist: trafilatura>=1.6.0
Requires-Dist: youtube-transcript-api>=0.6.0
Requires-Dist: PyYAML>=6.0
Requires-Dist: python-dateutil>=2.8.0
Requires-Dist: pydantic-settings>=2.10.1
Requires-Dist: fastapi>=0.116.1
Requires-Dist: uvicorn>=0.35.0
Requires-Dist: lxml<6
Requires-Dist: fastmcp>=2.12.4
Requires-Dist: jambo>=0.1.3.post2
Dynamic: license-file
